MultiColumnLabelEncoder.py
MultiColumnLabelEncoder-1.1.3.dist-info/LICENSE
MultiColumnLabelEncoder-1.1.3.dist-info/METADATA
MultiColumnLabelEncoder-1.1.3.dist-info/WHEEL
MultiColumnLabelEncoder-1.1.3.dist-info/top_level.txt
MultiColumnLabelEncoder-1.1.3.dist-info/RECORD
