Metadata-Version: 2.1
Name: MultiColumnLabelEncoder
Version: 1.1.3
Summary: Label Encoder which is used for encoding multiple categorical columns in a dataframe and inversing it
Author: Muttineni Sai Rohith
Classifier: Programming Language :: Python :: 3
Classifier: License :: OSI Approved :: MIT License
Classifier: Operating System :: OS Independent
Requires-Python: >=3.6
License-File: LICENSE
